safety_schemas/__init__.py
safety_schemas/config/schemas/v3_0/__init__.py
safety_schemas/config/schemas/v3_0/main.py
safety_schemas/models/__init__.py
safety_schemas/models/base.py
safety_schemas/models/config.py
safety_schemas/models/config_protocol.py
safety_schemas/models/ecosystem.py
safety_schemas/models/file.py
safety_schemas/models/git.py
safety_schemas/models/metadata.py
safety_schemas/models/package.py
safety_schemas/models/policy_file.py
safety_schemas/models/project.py
safety_schemas/models/report_protocol.py
safety_schemas/models/result.py
safety_schemas/models/scan.py
safety_schemas/models/specification.py
safety_schemas/models/telemetry.py
safety_schemas/models/util.py
safety_schemas/models/vulnerability.py
safety_schemas/models/api/__init__.py
safety_schemas/models/api/events.py
safety_schemas/models/events/__init__.py
safety_schemas/models/events/base.py
safety_schemas/models/events/constants.py
safety_schemas/models/events/context.py
safety_schemas/models/events/types.py
safety_schemas/models/events/payloads/__init__.py
safety_schemas/models/events/payloads/main.py
safety_schemas/models/events/payloads/onboarding.py
safety_schemas/report/__init__.py
safety_schemas/report/schemas/v3_0/__init__.py
safety_schemas/report/schemas/v3_0/constants.py
safety_schemas/report/schemas/v3_0/main.py
safety_schemas-0.0.17.dist-info/METADATA
safety_schemas-0.0.17.dist-info/WHEEL
safety_schemas-0.0.17.dist-info/licenses/LICENSE
safety_schemas-0.0.17.dist-info/RECORD
